takopi_slack_plugin/__init__.py
takopi_slack_plugin/backend.py
takopi_slack_plugin/bridge.py
takopi_slack_plugin/client.py
takopi_slack_plugin/commands/__init__.py
takopi_slack_plugin/commands/dispatch.py
takopi_slack_plugin/commands/executor.py
takopi_slack_plugin/commands/file_transfer.py
takopi_slack_plugin/commands/reply.py
takopi_slack_plugin/config.py
takopi_slack_plugin/engine.py
takopi_slack_plugin/onboarding.py
takopi_slack_plugin/outbox.py
takopi_slack_plugin/overrides.py
takopi_slack_plugin/thread_sessions.py
takopi_slack_plugin-0.2.11.dist-info/WHEEL
takopi_slack_plugin-0.2.11.dist-info/entry_points.txt
takopi_slack_plugin-0.2.11.dist-info/METADATA
takopi_slack_plugin-0.2.11.dist-info/RECORD
