Metadata-Version: 2.3
Name: takopi-slack-plugin
Version: 0.2.11
Summary: Slack transport plugin for Takopi.
Keywords: takopi,slack,transport,plugin
Author: takopi contributors
License: MIT License
Classifier: License :: OSI Approved :: MIT License
Classifier: Programming Language :: Python :: 3
Classifier: Programming Language :: Python :: 3.14
Classifier: Programming Language :: Python :: 3 :: Only
Classifier: Operating System :: OS Independent
Requires-Dist: anyio>=4.12.0
Requires-Dist: httpx>=0.28.1
Requires-Dist: questionary>=2.1.1
Requires-Dist: takopi>=0.20.0
Requires-Dist: websockets>=12.0
Requires-Python: >=3.14
Project-URL: Homepage, https://zkp2p.xyz
